dbt/__init__.py
dbt/adapters/__init__.py
dbt/adapters/excel/__init__.py
dbt/adapters/excel/__version__.py
dbt/adapters/excel/connections.py
dbt/adapters/excel/impl.py
dbt/adapters/excel/relation.py
dbt/include/__init__.py
dbt/include/excel/__init__.py
dbt/include/excel/dbt_project.yml
dbt/include/excel/macros/adapters.sql
dbt/include/excel/macros/materializations/external.sql
dbt/include/excel/macros/utils/external_location.sql
dbt_excel-1.4.0rc2.dist-info/LICENSE
dbt_excel-1.4.0rc2.dist-info/METADATA
dbt_excel-1.4.0rc2.dist-info/WHEEL
dbt_excel-1.4.0rc2.dist-info/top_level.txt
dbt_excel-1.4.0rc2.dist-info/RECORD
