Metadata-Version: 2.1
Name: dbt-excel
Version: 1.4.0rc2
Summary: The excel adapter plugin for dbt (data build tool)
Home-page: https://github.com/godatadriven/dbt-excel
Author: Cor Zuurmond,Dumky de Wilde,Juan Perafan,Henk Griffioen
Author-email: Cor.Zuurmond@xebia.com,Dumky.deWilde@xebia.com,Henk.Griffioen@xebia.com, juan.perafan@xebia.com
License: UNKNOWN
Platform: UNKNOWN
License-File: LICENSE
Requires-Dist: dbt-duckdb (~=1.4.0)
Requires-Dist: pandas (<2.0.0,>=1.0.0)
Provides-Extra: glue
Requires-Dist: boto3 ; extra == 'glue'
Requires-Dist: mypy-boto3-glue ; extra == 'glue'
